## 二、JVM内存模型之02：程序计数器

### 1、什么是程序计数器

  程序计数器（Program Counter Register）是一块较小的内存空间（具体有多小，稍后分析），它可以看做是当前线程所执行的字节码的行号指示器。

Java代码编译后的字节码在未经过JIT（实时编译器）编译前，其执行方式是通过“字节码解释器”进行解释执行。简单的工作原理为解释器读取装载入内存的字节码，按照顺序读取字节码指令。读取一个指令后，将该指令“翻译”成固定的操作，并根据这些操作进行分值、循环、跳转、异常处理、线程恢复等流程。

 	看到这里，可能会产生“这个程序计数器是多余的”的疑问，既然字节码是有顺序的一行行指令，那么按照顺序执行下去，即便是分支跳转这样的流程，跳转到指定的指令处按顺序继续执行是完全能够保证程序的执行顺序的，为什么专门需要一个程序计数器呢？

​	假设程序永远只有一个线程，完全不需要程序计数器，但实际上程序是通过多个线程协同合作执行的。首先，我们需要知道JVM多线程的实现方式。JVM的多线程是通过线程轮流切换并分配处理器执行时间（`CPU时间片`）的方式来实现的，在任何一个确定的时刻、一个处理器都只会执行一条线程中的指令。因此，为了线程切换后能恢复到正确的执行位置，每条线程都需要有一个独立的程序计数器，各条线程之间计数器互不影响，独立存储。

> CPU 时间片即 CPU 分配给各个程序的时间，每个线程被分配一个时间段，称作它的时间片，即该进程允许运行的时间，使各个程序从表面上看是同时进行的。如果在时间片结束时进程还在运行，则 CPU 将被剥夺并分配给另一个进程。如果进程在时间片结束前阻塞或结束，则 CPU 当即进行切换。而不会造成 CPU 资源浪费。在宏观上：我们可以同时打开多个应用程序，每个程序并行不悖，同时运行。但在微观上：由于只有一个 CPU，一次只能处理程序要求的一部分，如何处理公平，一种方法就是引入时间片，每个程序轮流执行。



### 2、特点

- 线程私有。
- 占用内存小。
- 当前执行java方法时，这个计数器记录的是正在执行的虚拟机字节码指令的地址。
- 当执行的是**Native**方法时，这个计数器值则为空（Undefined）,因为native方法是java通过JNI直接调用本地C/C++库，可以近似的认为native方法相当于C/C++暴露给java的一个接口，java通过调用这个接口从而调用到C/C++方法。由于该方法是通过C/C++而不是java进行实现。那么自然无法产生相应的字节码，并且C/C++执行时的内存分配是由自己语言决定的，而不是由JVM决定的。
- Java虚拟机规范中唯一一个没有规定任何OutOfMemoryError情况的区域。



### 3、代码示例

根据一段简单的代码，大概了解一下程序计数器中存储哪些内容。

```java
package com.xuge.demo1;
public class ProgramCounterDemo {

	public int add() {
		int a = 100;
		int b = 200;
		int c = 300;
		return (a+b)*c;
	}
}
```

该类编译后成class文件后，可通过 ` javap -c 类名`的命令，如：  `javap -c ProgramCounterDemo` 来查看其生成的字节码指令相关信息

```c++
public class com.xuge.demo1.ProgramCounterDemo {
  public com.xuge.demo1.ProgramCounterDemo();
    Code:
       0: aload_0
       1: invokespecial #1                  // Method java/lang/Object."<init>":()V
       4: return

  public int add();
    Code:
       0: bipush        100   // 将数值100 加载到操作数栈
       2: istore_1  		  //将一个数值从操作数栈存储到局部变量表 1 的位置
       3: sipush        200   //将数值200 加载到操作数栈
       6: istore_2
       7: sipush        300
      10: istore_3
      11: iload_1  // 将局部变量表 1 位置的数值加载到操作数栈
      12: iload_2  // 将局部变量表 2 位置的数值加载到操作数栈
      13: iadd     // 执行相加计算
      14: iload_3  // 将局部变量表 3 位置的数值加载到操作数栈
      15: imul     // 执行相乘计算
      16: ireturn  //返回
}
```

其中  `0: bipush`  、`2: istore_1`  前面的数字 `0`、 `2`，即表示当前字节码指令的偏移地址，后面 `bipush`  `istore` 是相关的操作指令。

随着方法 `add()`的执行，当前线程的程序计数器会不断的改变其存储的字节码指令地址。

由此可见，程序计数器 并不会占用多少存储空间，当然，也不会出现内存溢出的情况。

### 4、关于Native方法的介绍